MANIFEST.in
README.rst
requirements-tests.txt
requirements.txt
setup.py
dj_web_rich_object/__init__.py
dj_web_rich_object/apps.py
dj_web_rich_object/functional_tests.py
dj_web_rich_object/models.py
dj_web_rich_object/views.py
dj_web_rich_object/admin/__init__.py
dj_web_rich_object/admin/forms.py
dj_web_rich_object/admin/modeladmins.py
dj_web_rich_object/migrations/0001_initial.py
dj_web_rich_object/migrations/0002_auto_20161124_0937.py
dj_web_rich_object/migrations/0003_auto_20161124_1414.py
dj_web_rich_object/migrations/0004_auto_20161214_1706.py
dj_web_rich_object/migrations/0005_auto_20161215_0835.py
dj_web_rich_object/migrations/0006_auto_20161219_1809.py
dj_web_rich_object/migrations/0007_webrichobject_video.py
dj_web_rich_object/migrations/0008_auto_20161229_0523.py
dj_web_rich_object/migrations/0009_auto_20161230_1204.py
dj_web_rich_object/migrations/0010_webrichobject_audio.py
dj_web_rich_object/migrations/0011_webrichobject_tags.py
dj_web_rich_object/migrations/0012_auto_20190916_1351.py
dj_web_rich_object/migrations/0013_tag_parent.py
dj_web_rich_object/migrations/0014_tag_is_hidden.py
dj_web_rich_object/migrations/__init__.py
dj_web_rich_object/templates/admin/dj_web_rich_object/change_form.html
dj_web_rich_object/templates/wro/.widget_video.html.swp
dj_web_rich_object/templates/wro/base.html
dj_web_rich_object/templates/wro/widget_article.html
dj_web_rich_object/templates/wro/widget_image.html
dj_web_rich_object/templates/wro/widget_object.html
dj_web_rich_object/templates/wro/widget_product.html
dj_web_rich_object/templates/wro/widget_profile.html
dj_web_rich_object/templates/wro/widget_video.html
dj_web_rich_object/templates/wro/widget_website.html
dj_web_rich_object/templatetags/__init__.py
dj_web_rich_object/templatetags/wro.py
dj_web_rich_object/tests/__init__.py
dj_web_rich_object/tests/factories.py
dj_web_rich_object/tests/settings.py
dj_web_rich_object/tests/urls.py
dj_web_rich_object/tests/test_models/__init__.py
django_web_rich_object.egg-info/PKG-INFO
django_web_rich_object.egg-info/SOURCES.txt
django_web_rich_object.egg-info/dependency_links.txt
django_web_rich_object.egg-info/not-zip-safe
django_web_rich_object.egg-info/requires.txt
django_web_rich_object.egg-info/top_level.txt