Metadata-Version: 1.1
Name: django-web-rich-object
Version: 0.3.2
Summary: Reusable app made for handle web rich objects
Home-page: https://github.com/ZuluPro/django-web-rich-object
Author: Anthony Monthe (ZuluPro)
Author-email: anthony.monthe@gmail.com
License: BSD
Keywords: web,django,opengraph,web-rich-object,facebook
Platform: UNKNOWN
Classifier: Framework :: Django
Classifier: Development Status :: 5 - Production/Stable
Classifier: Environment :: Web Environment
Classifier: Programming Language :: Python
Classifier: Programming Language :: Python :: 3
Classifier: Intended Audience :: Developers
Classifier: Operating System :: OS Independent
Classifier: License :: OSI Approved :: BSD License
Classifier: Topic :: Software Development :: Libraries :: Python Modules
